prtg_utils/__init__.py
prtg_utils/history.py
prtg_utils/history_cmdline.py
prtg_utils/utils.py
prtg_utils-0.9.4.dist-info/LICENSE.txt
prtg_utils-0.9.4.dist-info/METADATA
prtg_utils-0.9.4.dist-info/WHEEL
prtg_utils-0.9.4.dist-info/entry_points.txt
prtg_utils-0.9.4.dist-info/top_level.txt
prtg_utils-0.9.4.dist-info/RECORD
